pantsbuild.pants.contrib.findbugs-1.28.0-py3.6-nspkg.pth
pants/contrib/findbugs/__init__.py
pants/contrib/findbugs/register.py
pants/contrib/findbugs/tasks/__init__.py
pants/contrib/findbugs/tasks/findbugs.py
pantsbuild.pants.contrib.findbugs-1.28.0.dist-info/METADATA
pantsbuild.pants.contrib.findbugs-1.28.0.dist-info/WHEEL
pantsbuild.pants.contrib.findbugs-1.28.0.dist-info/entry_points.txt
pantsbuild.pants.contrib.findbugs-1.28.0.dist-info/namespace_packages.txt
pantsbuild.pants.contrib.findbugs-1.28.0.dist-info/top_level.txt
pantsbuild.pants.contrib.findbugs-1.28.0.dist-info/zip-safe
pantsbuild.pants.contrib.findbugs-1.28.0.dist-info/RECORD
